{"783320404702":{"price":899.9,"min":899.9,"max":899.9,"productName":"Perfume Rose Goldea Blossom Delight Eau De Parfum Feminino Bvlgari 75ml","updatedAt":"2026-07-22T21:36:56.884Z"},"783320404726":{"price":569.9,"min":569.9,"max":569.9,"productName":"Perfume Feminino Rose Goldea Blossom Delight Bvlgari Eau De Parfum 30ml","updatedAt":"2026-07-22T21:36:56.884Z"},"783320413841":{"price":789.9,"min":789.9,"max":789.9,"productName":"Perfume Masculino Man In Black Bvlgari Eau De Parfum 60ml","updatedAt":"2026-07-22T21:36:56.884Z"},"783320413858":{"price":979.9,"min":979.9,"max":979.9,"productName":"Perfume Bvlgari Man In Black Eau De Parfum Masculino 100ml","updatedAt":"2026-07-22T21:36:56.884Z"},"783320414787":{"price":1199.9,"min":1199.9,"max":1199.9,"productName":"Perfume Masculino Man In Black Bvlgari Eau De Parfum 150ml","updatedAt":"2026-07-22T21:36:56.884Z"},"783320417023":{"price":825,"min":799.9,"max":825,"productName":"Perfume Feminino Rose Goldea Blossom Delight Bvlgari Eau De Toilette 75ml","updatedAt":"2026-07-22T21:36:56.884Z"},"78332041946":{"price":980,"min":980,"max":980,"productName":"Perfume Masculino Man Rain Essence Bvlgari Eau De Parfum 100ml","updatedAt":"2026-07-22T21:36:56.884Z"},"783320419461":{"price":979.9,"min":979.9,"max":979.9,"productName":"Perfume Bvlgari Man Rain Essence Eau De Parfum Masculino 100ml","updatedAt":"2026-07-22T21:36:56.884Z"},"783320419485":{"price":799,"min":759.9,"max":799,"productName":"Perfume Bvlgari Man Rain Essence Eau De Parfum Masculino 60ml","updatedAt":"2026-07-22T21:36:56.884Z"},"783320420566":{"price":935,"min":935,"max":935,"productName":"Perfume Omnia Crystalline Eau De Toilette Feminino Bvlgari 100ml","updatedAt":"2026-07-22T21:36:56.884Z"},"783320420573":{"price":680,"min":680,"max":699.9,"productName":"Perfume Omnia Crystalline Eau De Toilette Feminino Bvlgari 50ml","updatedAt":"2026-07-22T21:36:56.884Z"},"783320420580":{"price":499.9,"min":499.9,"max":499.9,"productName":"Perfume Omnia Crystalline Eau De Toilette Feminino Bvlgari 30ml","updatedAt":"2026-07-22T21:36:56.884Z"},"783320420610":{"price":979.7,"min":899.9,"max":979.7,"productName":"Perfume Feminino Omnia Amethyste Bvlgari Eau De Toilette 100ml","updatedAt":"2026-07-22T21:36:56.884Z"},"783320420627":{"price":680,"min":680,"max":680,"productName":"Perfume Feminino Omnia Amethyste Bvlgari Eau De Toilette 50ml","updatedAt":"2026-07-22T21:36:56.884Z"},"783320420634":{"price":520,"min":475,"max":520,"productName":"Omnia Amethyste Bvlgari Eau De Toilette Perfume Feminino 30ml","updatedAt":"2026-07-22T21:36:56.884Z"},"783320420672":{"price":999.9,"min":935,"max":999.9,"productName":"Bvlgari Omnia Coral Eau De Toilette - Perfume Feminino 100ml","updatedAt":"2026-07-22T21:36:56.884Z"},"783320421297":{"price":1150,"min":1150,"max":1150,"productName":"Perfume Masculino Pour Homme Bvlgari Eau De Parfum 100ml","updatedAt":"2026-07-22T21:36:56.884Z"},"783320423369":{"price":949,"min":949,"max":1250,"productName":"Perfume Feminino Bvlgari Omnia Crystalline Eau De Parfum 100ml","updatedAt":"2026-07-22T21:36:56.884Z"},"783320461019":{"price":759.9,"min":759.9,"max":759.9,"productName":"Perfume Bvlgari Man Wood Essence Edp Masculino 60ml","updatedAt":"2026-07-22T21:36:56.884Z"}}