{"78602731":{"price":12.99,"min":12.99,"max":12.99,"productName":"Chocolate Kinder Joy 20g","updatedAt":"2026-07-22T21:36:56.886Z"},"7861002901831":{"price":12.49,"min":12.49,"max":12.49,"productName":"Pastilha Tic Tac Menta 49g","updatedAt":"2026-07-22T21:36:56.886Z"},"7861002901855":{"price":12.49,"min":12.49,"max":12.49,"productName":"Pastilha Tic Tac Laranja 49g","updatedAt":"2026-07-22T21:36:56.886Z"},"786471696101":{"price":29.9,"min":29.9,"max":29.9,"productName":"Massa Tipo Lasanha Konjac 270g","updatedAt":"2026-07-22T21:36:56.886Z"},"786471696309":{"price":29.9,"min":29.9,"max":29.9,"productName":"Massa Tipo Noodles Konjac 270g","updatedAt":"2026-07-22T21:36:56.886Z"},"786471696316":{"price":29.9,"min":29.9,"max":29.9,"productName":"Massa Tipo Cabelo De Anjo Konjac 270g","updatedAt":"2026-07-22T21:36:56.886Z"},"786471696323":{"price":29.9,"min":29.9,"max":29.9,"productName":"Massa Tipo Fettuccine Konjac 270g","updatedAt":"2026-07-22T21:36:56.886Z"},"7866889932374":{"price":101.4,"min":101.4,"max":101.4,"productName":"Kit 3 Faixas Elásticas De Exercicios Hip Resistance Bands","updatedAt":"2026-07-22T21:36:56.886Z"},"7866889933746":{"price":25.87,"min":25.87,"max":25.87,"productName":"Urinol Feminino Portátil De Emergência Em Silicone","updatedAt":"2026-07-22T21:36:56.886Z"}}