{"194133273353":{"price":249.9,"min":249.9,"max":249.9,"productName":"Garrafa Zoo Lhama - Skip Hop Verde","updatedAt":"2026-07-22T21:34:56.943Z"},"194133372216":{"price":167.91,"min":167.91,"max":167.91,"productName":"Kit Lanche Raposa Skip Hop","updatedAt":"2026-07-22T21:34:56.943Z"},"194133416804":{"price":126,"min":126,"max":126,"productName":"Potinho Snack Flamingo Skip Hop","updatedAt":"2026-07-22T21:34:56.943Z"},"194135560857":{"price":89.26,"min":89.26,"max":89.26,"productName":"Talheres Koala Skip Hop","updatedAt":"2026-07-22T21:34:56.943Z"},"194346065233":{"price":260.22,"min":260.22,"max":260.22,"productName":"ÓLEO DE PEIXE OMEGA 3 1000 MG 60 SOFTGELS SABOR LIMãO - SPRING VALLEY","updatedAt":"2026-07-22T21:34:56.943Z"},"194346377398":{"price":195.64,"min":195.64,"max":195.64,"productName":"Shilajit 500 Mg, 60 Cápsulas - Spring Valley","updatedAt":"2026-07-22T21:34:56.943Z"},"19474007262":{"price":33.9,"min":33.9,"max":33.9,"productName":"Creme Cilios #Wsp","updatedAt":"2026-07-22T21:34:56.943Z"}}