{"2314558875859":{"price":73.99,"min":73.99,"max":73.99,"productName":"Kit Lavitan Vitamina Cabelos e Unhas 60 Cápsulas - 2 Unidades","updatedAt":"2026-07-22T21:34:56.968Z"},"2314735077625":{"price":64.89,"min":64.89,"max":64.89,"productName":"Kit com 2 - Loção Hidratante Oaz Creme de Ureia de 10% 300Ml","updatedAt":"2026-07-22T21:34:56.968Z"},"2318547898584":{"price":59,"min":59,"max":59,"productName":"Adesivo para Alívio da Febre Bye Bye Fever Criança - 2 Pacotes com 2 Unidades Cada","updatedAt":"2026-07-22T21:34:56.968Z"}}