{"30158078":{"price":225.9,"min":225.9,"max":225.9,"productName":"Shampoo L'Oréal Professionnel Metal Detox Cabelos Danificados 300ml","updatedAt":"2026-07-22T21:34:57.018Z"},"30160606":{"price":323.9,"min":323.9,"max":323.9,"productName":"Máscara de Cabelo L'Oréal Professionnel Metal Detox Cabelos Coloridos 250ml","updatedAt":"2026-07-22T21:34:57.018Z"},"30161153":{"price":287.9,"min":287.9,"max":287.9,"productName":"Leave-In L'Oréal Professionnel Metal Detox Cabelos Danificados 100ml","updatedAt":"2026-07-22T21:34:57.018Z"},"30163478":{"price":364.9,"min":364.9,"max":364.9,"productName":"Máscara de Cabelo L'Oréal Professionnel Metal Detox Cabelos Coloridos 500ml","updatedAt":"2026-07-22T21:34:57.018Z"},"3010017000006":{"price":287.99,"min":287.99,"max":287.99,"productName":"Kit Bio-extratus Mais Liso ( 3 Produtos )","updatedAt":"2026-07-22T21:34:57.018Z"},"3014260011048":{"price":90.26,"min":90.26,"max":90.26,"productName":"Escova de Dente Oral B Vlinical Pro-Flex","updatedAt":"2026-07-22T21:34:57.018Z"},"3014260014445":{"price":22.9,"min":20.94,"max":36.02,"productName":"Escova de Dente Oral-B Complete 5 Ações de Limpeza Macia N°40 com 2 unidades","updatedAt":"2026-07-22T21:34:57.018Z"},"3014260019723":{"price":36.74,"min":36.74,"max":36.74,"productName":"Escova Kids Mickey Oral-B Simples","updatedAt":"2026-07-22T21:34:57.018Z"},"3014260274917":{"price":295.65,"min":295.65,"max":295.65,"productName":"Carga de Laminas de Barbear Gillette Mach3 Turbo C/ 4 unidades","updatedAt":"2026-07-22T21:34:57.018Z"},"3014260278922":{"price":118.4,"min":25.42,"max":118.4,"productName":"Escova Infantil Stages Pro-Saúde 8+Anos","updatedAt":"2026-07-22T21:34:57.018Z"},"3014260278939":{"price":118.4,"min":22.62,"max":118.4,"productName":"Escova Infantil Stages 1","updatedAt":"2026-07-22T21:34:57.018Z"},"3014260279264":{"price":25.9,"min":25.9,"max":25.9,"productName":"Escova de Dente Infantil Oral B Stages N°3 Disney 5-7 Anos Macia com 1 unidade","updatedAt":"2026-07-22T21:34:57.018Z"},"3014260323998":{"price":57.18,"min":57.18,"max":57.18,"productName":"Escova de Dentes Infantil Foral-B Zooth Hello Kitty","updatedAt":"2026-07-22T21:34:57.018Z"},"3014260833176":{"price":26.32,"min":6.52,"max":26.32,"productName":"Escova Classic Limpeza Brilhante Oral-B Simples","updatedAt":"2026-07-22T21:34:57.018Z"},"3014260833183":{"price":70.04,"min":70.04,"max":70.04,"productName":"Escova Dental Oral B 123 Média com Protetor Higiênico Embalagem com 12 unidades","updatedAt":"2026-07-22T21:34:57.018Z"}}