{"3220660317585":{"price":2199,"min":2199,"max":2199,"productName":"Cadeira de Refeição Minla Maxi-cosi - Essential Graphite","updatedAt":"2026-07-22T21:34:58.090Z"},"3220660336791":{"price":849,"min":849,"max":849,"productName":"Babá Eletrônica See Maxi-cosi White","updatedAt":"2026-07-22T21:34:58.090Z"},"3220660337965":{"price":3899,"min":3899,"max":3899,"productName":"Carrinho de Bebê Anna Luxe Maxi-cosi Twillic Grey","updatedAt":"2026-07-22T21:34:58.090Z"},"3220660341061":{"price":2199,"min":2199,"max":2199,"productName":"Berço Iora Air Maxi-cosi Beyond Graphite","updatedAt":"2026-07-22T21:34:58.090Z"},"3222297123874":{"price":278.99,"min":278.99,"max":278.99,"productName":"Kit com 40 Algodão Hidrofilo Quadradinho 100% Algodão Macio","updatedAt":"2026-07-22T21:34:58.090Z"},"3225669858985":{"price":200,"min":200,"max":200,"productName":"Kit Omega 3 1000Mg 120 Cápsulas Catarinense 3 Unidades","updatedAt":"2026-07-22T21:34:58.091Z"}}