{"3442151000770":{"price":219.98,"min":219.98,"max":219.98,"productName":"Monogramme Yves de Sistelle Eau de Parfum 100ml - Perfume Feminino","updatedAt":"2026-07-22T21:34:58.262Z"},"3442151001593":{"price":219.98,"min":219.98,"max":219.98,"productName":"Forbidden Dreams Yves de Sistelle Eau de Parfum 100ml","updatedAt":"2026-07-22T21:34:58.262Z"},"3442151009674":{"price":219.11,"min":219.11,"max":219.11,"productName":"Aviator Code Eau De Toilette 100ml","updatedAt":"2026-07-22T21:34:58.262Z"},"3442151009827":{"price":295.11,"min":295.11,"max":295.11,"productName":"Perfume Feminino Yves De Sistelle Galice Sensuelle 100ml","updatedAt":"2026-07-22T21:34:58.262Z"},"3442180000093":{"price":424.03,"min":424.03,"max":424.03,"productName":"Perfume Feminino Blanc Parfum Courreges (nova Embalagem) 90 Ml Eau de Parfum","updatedAt":"2026-07-22T21:34:58.262Z"}}