{"3145891054552":{"price":878.88,"min":878.88,"max":878.88,"productName":"Chanel Nº 5 Feminino Eau de Toilette 50ml","updatedAt":"2026-07-22T21:35:27.266Z"},"3145891071900":{"price":3215,"min":3048.33,"max":3215,"productName":"Bleu de Chanel Parfum Masculino-150 Ml","updatedAt":"2026-07-22T21:35:27.266Z"},"3145891073607":{"price":1518,"min":1518,"max":1518,"productName":"Bleu de Chanel Eau de Parfum Pour Homme - Chanel 100ml","updatedAt":"2026-07-22T21:35:27.266Z"},"3145891073706":{"price":2815,"min":2815,"max":2815,"productName":"Bleu de Chanel Eau de Parfum Masculino-150 Ml","updatedAt":"2026-07-22T21:35:27.266Z"},"3145891074604":{"price":1009,"min":1009,"max":1715,"productName":"Bleu de Chanel Eau de Toilette Masculino-100 Ml","updatedAt":"2026-07-22T21:35:27.266Z"},"3145891162608":{"price":1099,"min":1099,"max":1099,"productName":"Coco Mademoiselle L´eau Privée Chanel Eau de Parfum Feminino-100 Ml","updatedAt":"2026-07-22T21:35:27.266Z"},"3145891165203":{"price":1501.18,"min":1501.18,"max":1501.18,"productName":"Chanel Coco Mademoiselle Feminino Eau de Parfum 100ml","updatedAt":"2026-07-22T21:35:27.266Z"},"3145891169508":{"price":779,"min":779,"max":1315,"productName":"Óleo Corporal Coco Mademoiselle Chanel Unissex-200 Ml","updatedAt":"2026-07-22T21:35:27.266Z"},"3145891205251":{"price":1454,"min":1454,"max":1454,"productName":"Gabrielle Eau de Parfum Feminino - Chanel 100ml","updatedAt":"2026-07-22T21:35:27.266Z"},"3145891214604":{"price":1501.9,"min":1501.9,"max":1501.9,"productName":"Chanel Allure Homme Eau de Toilette 100ml","updatedAt":"2026-07-22T21:35:27.266Z"},"3145891233209":{"price":1509.98,"min":1509.98,"max":1509.98,"productName":"Chanel Allure Homme Sport Cologne 100ml","updatedAt":"2026-07-22T21:35:27.266Z"},"3145891234503":{"price":1011,"min":1011,"max":1011,"productName":"Coco Eau de Toilette Feminino - Chanel 50ml","updatedAt":"2026-07-22T21:35:27.266Z"},"3145891235609":{"price":2065,"min":2065,"max":2065,"productName":"Allure Homme Sport Eau Extrême Chanel Eau de Parfum Masculino-100 Ml","updatedAt":"2026-07-22T21:35:27.266Z"},"3145891236309":{"price":1009,"min":1009,"max":1189,"productName":"Allure Homme Sport Chanel Eau de Toilette Maculino-100 Ml","updatedAt":"2026-07-22T21:35:27.266Z"},"314589126200":{"price":2181.67,"min":2181.67,"max":2181.67,"productName":"Chance Eau Splendide Chanel Eau de Parfum Feminino-100 Ml","updatedAt":"2026-07-22T21:35:27.266Z"},"3145891274608":{"price":1219,"min":1219,"max":1439,"productName":"Allure Homme Édition Blanche Chanel Eau de Parfum Masculino-100 Ml","updatedAt":"2026-07-22T21:35:27.266Z"},"3145891361506":{"price":2281.67,"min":2281.67,"max":2281.67,"productName":"Chance Eau Fraîche Chanel Eau de Parfum Feminino-100 Ml","updatedAt":"2026-07-22T21:35:27.266Z"},"3145891364200":{"price":1439.98,"min":1439.98,"max":1439.98,"productName":"Chanel Chance Eau Fraîche Eau de Toilette 100ml","updatedAt":"2026-07-22T21:35:27.266Z"},"3147280062452":{"price":898.46,"min":898.46,"max":898.46,"productName":"Perfume Amor Amor Feminino Eau de Toilette - Cacharel 100ml","updatedAt":"2026-07-22T21:35:27.266Z"},"3147758029383":{"price":793,"min":793,"max":793,"productName":"Miracle Lâncome Eau de Parfum 100Ml - Perfume Feminino","updatedAt":"2026-07-22T21:35:27.266Z"},"3147758029406":{"price":609,"min":549.9,"max":881.67,"productName":"Miracle Lancôme Eau de Parfum Feminino-30 Ml","updatedAt":"2026-07-22T21:35:27.266Z"},"3147758030334":{"price":319,"min":319,"max":419,"productName":"Bi-Facil Lancôme - Demaquilante 125ml","updatedAt":"2026-07-22T21:35:27.266Z"},"3147758034905":{"price":479,"min":479,"max":815,"productName":"Trésor Lancôme Eau de Parfum Feminino-30 Ml","updatedAt":"2026-07-22T21:35:27.267Z"},"3147758034929":{"price":1410.43,"min":1410.43,"max":1410.43,"productName":"Perfume Feminino Tresor Lancome 100 Ml Eau de Parfum","updatedAt":"2026-07-22T21:35:27.267Z"},"3147758051216":{"price":528.22,"min":528.22,"max":528.22,"productName":"Bocage Déodorant Spray Sec Douceur Lancôme - Desodorante Aerosol 150g","updatedAt":"2026-07-22T21:35:27.267Z"},"3147758155112":{"price":999.91,"min":999.91,"max":1215,"productName":"Perfume Poême Feminino Eau de Parfum 100ml - Lancôme","updatedAt":"2026-07-22T21:35:27.267Z"},"3147758235500":{"price":1183.29,"min":1183.29,"max":1183.29,"productName":"Perfume Lancôme Hypnôse - Eau de Parfum - 75 Ml","updatedAt":"2026-07-22T21:35:27.267Z"},"3147758235548":{"price":700,"min":563.99,"max":700,"productName":"Hypnôse Lancôme Eau de Parfum 30Ml - Perfume Feminino","updatedAt":"2026-07-22T21:35:27.267Z"}}