{"33000000015":{"price":49.95,"min":49.95,"max":49.95,"productName":"Esmalte Super Lustrous Optimistic Nº 290 14,7ml - Revlon","updatedAt":"2026-07-22T21:35:27.327Z"},"33000000954":{"price":65.52,"min":65.52,"max":65.52,"productName":"Esmalte Revlon Super Lustrous 14,7Ml Divine","updatedAt":"2026-07-22T21:35:27.327Z"},"33000003085":{"price":65.52,"min":65.52,"max":65.52,"productName":"Esmalte Revlon Super Lustrous Nail Enamel Renovation Posh","updatedAt":"2026-07-22T21:35:27.327Z"},"3305400180053":{"price":950.91,"min":950.91,"max":950.91,"productName":"Perfume Feminino Ambre Molinard 75 Ml Eau de Parfum","updatedAt":"2026-07-22T21:35:27.327Z"}}