{"9786526100332":{"price":10.05,"min":10.05,"max":10.05,"productName":"Livro de Atividades Ciranda Cultural Turma da Mônica","updatedAt":"2026-07-22T21:34:52.217Z"},"9786526104767":{"price":10.05,"min":10.05,"max":10.05,"productName":"Livro de Passatempos Ciranda Cultural + 50 Atividades Eletrizantes","updatedAt":"2026-07-22T21:34:52.217Z"},"9786526104774":{"price":10.05,"min":10.05,"max":10.05,"productName":"Livro de Passatempo Ciranda Cultural + 50 Atividades Incriveis","updatedAt":"2026-07-22T21:34:52.218Z"},"9786555000498":{"price":10.05,"min":10.05,"max":10.05,"productName":"Livro de Colorir Ciranda Cultural Aquarela Princesas","updatedAt":"2026-07-22T21:34:52.218Z"},"9786555001747":{"price":10.05,"min":10.05,"max":10.05,"productName":"Livro de Colorir Ciranda Cultural Barbie","updatedAt":"2026-07-22T21:34:52.218Z"},"9786555001761":{"price":10.05,"min":10.05,"max":10.05,"productName":"Livro de Atividades Ciranda Passatempos da Patrulha","updatedAt":"2026-07-22T21:34:52.218Z"},"9786555001778":{"price":10.05,"min":10.05,"max":10.05,"productName":"Livro Infantil Hot Wheels Desafios Alucinantes Ciranda Cultural","updatedAt":"2026-07-22T21:34:52.218Z"},"9786555002966":{"price":10.05,"min":10.05,"max":10.05,"productName":"Livro de Colorir Ciranda Mandalas","updatedAt":"2026-07-22T21:34:52.218Z"},"9786555006636":{"price":10.05,"min":10.05,"max":10.05,"productName":"Bíblia para Crianças Ciranda Cultural","updatedAt":"2026-07-22T21:34:52.218Z"},"9786555009279":{"price":10.05,"min":10.05,"max":10.05,"productName":"Livro de Colorir Olhinhos Mágicos Ciranda Cultural","updatedAt":"2026-07-22T21:34:52.218Z"},"9786555165753":{"price":24.9,"min":24.9,"max":24.9,"productName":"Album Brochura Copa do Mundo 2026 Panini","updatedAt":"2026-07-22T21:34:52.218Z"},"9788538074298":{"price":10.05,"min":10.05,"max":10.05,"productName":"Livro de Atividades Ciranda Patrulha Canina","updatedAt":"2026-07-22T21:34:52.218Z"},"9788538076209":{"price":10.05,"min":10.05,"max":10.05,"productName":"Ciranda Livro de Caligrafia Turma da Mônica","updatedAt":"2026-07-22T21:34:52.218Z"},"9788538082521":{"price":10.05,"min":10.05,"max":10.05,"productName":"Livro Aquarela Patrulha Canina Ciranda Cultural","updatedAt":"2026-07-22T21:34:52.218Z"},"9788538083108":{"price":10.05,"min":10.05,"max":10.05,"productName":"Ciranda Livro Hot Wheels Universo Radical","updatedAt":"2026-07-22T21:34:52.218Z"},"9788538083139":{"price":10.05,"min":10.05,"max":10.05,"productName":"Livro de Colorir Ciranda Cultural Peppa Pig Festa Fantasia","updatedAt":"2026-07-22T21:34:52.218Z"},"9788538091615":{"price":10.05,"min":10.05,"max":10.05,"productName":"Livro para Colorir Ciranda Patrulha Canina 365 Desenhos","updatedAt":"2026-07-22T21:34:52.218Z"},"9788538098539":{"price":10.49,"min":10.49,"max":10.49,"productName":"Livro Ciranda Barbie 101 Desenho para Colorir","updatedAt":"2026-07-22T21:34:52.218Z"},"9788538099765":{"price":10.05,"min":10.05,"max":10.05,"productName":"Livro de Colorir Ciranda Cultural Princesas Aquarela","updatedAt":"2026-07-22T21:34:52.218Z"}}