{"4589546892226":{"price":179,"min":179,"max":179,"productName":"Ehoney Melty Moist Repair Passo 01 - Shampoo","updatedAt":"2026-07-22T21:35:55.674Z"},"4589546892233":{"price":199,"min":169,"max":199,"productName":"Ehoney Melty Moist Repair Treatment Passo 02 - Máscara Capilar","updatedAt":"2026-07-22T21:35:55.674Z"},"4589546892271":{"price":169,"min":169,"max":169,"productName":"Ehoney Melty Moist Repair Oil Passo 03 - Óleo Capilar","updatedAt":"2026-07-22T21:35:55.674Z"},"4589546895715":{"price":120.96,"min":120.96,"max":125,"productName":"&honey Deep Moist Body Wash - Gel para Banho 500ml","updatedAt":"2026-07-22T21:35:55.674Z"},"4589546897139":{"price":179,"min":179,"max":179,"productName":"Ehoney Milky Precious Ex Repair Treatment Passo 02 - Máscara Capilar","updatedAt":"2026-07-22T21:35:55.674Z"}}