{"7422887460402":{"price":95,"min":95,"max":95,"productName":"Banco de Cócoras Supermedy - unidade","updatedAt":"2026-07-22T21:35:57.204Z"},"742832179638":{"price":39.99,"min":39.99,"max":39.99,"productName":"Delineador Adesivo para os Olhos That Girl Gatinho Clássico 2 Pares","updatedAt":"2026-07-22T21:35:57.204Z"},"742832540322":{"price":177.59,"min":172.99,"max":199.9,"productName":"Kit Água Micelar Dermatológica Calmante Bioderma Sensibio H2O 250ml 2 Unidades","updatedAt":"2026-07-22T21:43:19.373Z"},"742832540339":{"price":161.9,"min":161.9,"max":161.9,"productName":"Kit Bioderma Sensibio H2O - Água Micelar 250 ml + Água Micelar 100 ml","updatedAt":"2026-07-22T21:35:57.205Z"},"742832695084":{"price":34.59,"min":34.59,"max":34.59,"productName":"Máscara Cirurgica Medtex Descartável 50 Unidades","updatedAt":"2026-07-22T21:35:57.205Z"}}