{"811068011347":{"price":240.61,"min":240.61,"max":240.61,"productName":"Perfume Feminino Dr Teal'S 240 ML Pure Epsom Salt Foot Creme With Shea Butter Aloe Vera & Vitamin","updatedAt":"2026-07-22T21:36:12.583Z"},"811068015253":{"price":310.65,"min":310.65,"max":310.65,"productName":"Perfume Feminino Dr Teal'S 170G Gentle Exfoliant Pure Epsom Salt Softening Remedy With Aloe&Coconut Oil","updatedAt":"2026-07-22T21:36:12.583Z"},"811068017905":{"price":305.56,"min":305.56,"max":305.56,"productName":"Perfume Feminino Dr Teal'S 260 ML Nourishing Coconut With Essensial Oils, Jojoba Oil, Sweet Almond And Cocoa Butter","updatedAt":"2026-07-22T21:36:12.583Z"},"811656030279":{"price":651.59,"min":651.59,"max":651.59,"productName":"Perfume Feminino Badgley Mischka 100 ML Eau De Parfum","updatedAt":"2026-07-22T21:36:12.583Z"},"811909015350":{"price":72.9,"min":72.9,"max":72.9,"productName":"Difusor de Aromas USB Serene Living Medlevensohn","updatedAt":"2026-07-22T21:36:12.583Z"},"811999023648":{"price":407.81,"min":407.81,"max":407.81,"productName":"Perfume Feminino Elizabeth And James 100 ML P/Corpo Oil","updatedAt":"2026-07-22T21:36:12.583Z"}}